setup.py
nom/__init__.py
nom/cli.py
nom/clipboard.py
nom/compile.py
nom/html2md.py
nom/md2html.py
nom/parsers.py
nom/server.py
nom/util.py
nom/watch.py
nom.egg-info/PKG-INFO
nom.egg-info/SOURCES.txt
nom.egg-info/dependency_links.txt
nom.egg-info/entry_points.txt
nom.egg-info/requires.txt
nom.egg-info/top_level.txt
nom/templates/browser.html
nom/templates/default.html
nom/templates/layout.html
nom/templates/preach.html