Metadata-Version: 2.1
Name: nom
Version: 1.5.1
Summary: tool for managing markdown notes
Home-page: https://github.com/frnsys/nom
Author: Francis Tseng
Author-email: f@frnsys.com
License: GPLv3
Platform: UNKNOWN
